gemiTask/__init__.py
gemiTask/gemini.py
gemiTask/main.py
gemiTask/storage.py
gemiTask/task.py
gemitask-0.1.4.dist-info/licenses/LICENSE
gemitask-0.1.4.dist-info/METADATA
gemitask-0.1.4.dist-info/WHEEL
gemitask-0.1.4.dist-info/entry_points.txt
gemitask-0.1.4.dist-info/top_level.txt
gemitask-0.1.4.dist-info/RECORD
