Metadata-Version: 2.4
Name: gemiTask
Version: 0.1.4
Summary: A CLI task manager with AI-powered task details generation
Home-page: https://github.com/sanjaymalladi/gemiTask
Author: Sanjay Malladi
Author-email: malladisanjay29@gmail.com
Project-URL: Bug Reports, https://github.com/sanjaymalladi/gemiTask/issues
Project-URL: Source, https://github.com/sanjaymalladi/gemiTask
Project-URL: Documentation, https://github.com/sanjaymalladi/gemiTask/blob/main/README.md
Keywords: cli,task-management,ai,gemini,productivity,todo,task-breakdown,project-management,terminal,command-line
Classifier: Development Status :: 4 - Beta
Classifier: Environment :: Console
Classifier: Intended Audience :: Developers
Classifier: License :: OSI Approved :: MIT License
Classifier: Operating System :: OS Independent
Classifier: Programming Language :: Python :: 3
Classifier: Programming Language :: Python :: 3.7
Classifier: Programming Language :: Python :: 3.8
Classifier: Programming Language :: Python :: 3.9
Classifier: Programming Language :: Python :: 3.10
Classifier: Programming Language :: Python :: 3.11
Classifier: Programming Language :: Python :: 3.12
Classifier: Topic :: Software Development :: Libraries :: Python Modules
Classifier: Topic :: Utilities
Classifier: Topic :: Office/Business :: Scheduling
Classifier: Topic :: System :: Systems Administration
Requires-Python: >=3.7
License-File: LICENSE
Requires-Dist: google-generativeai>=0.3.0
Requires-Dist: python-dateutil>=2.8.2
Requires-Dist: rich>=10.0.0
Requires-Dist: typing-extensions>=4.0.0
Requires-Dist: pydantic>=2.0.0
Dynamic: author
Dynamic: author-email
Dynamic: classifier
Dynamic: description
Dynamic: description-content-type
Dynamic: home-page
Dynamic: keywords
Dynamic: license-file
Dynamic: project-url
Dynamic: requires-dist
Dynamic: requires-python
Dynamic: summary
